{
  "trial_id": 5,
  "seed": 1024,
  "completed": true,
  "dry_run": false,
  "elapsed_sec": 1740.6,
  "timestamp": "2026-03-08T05:08:23.810970",
  "summary": {
    "acc_a_total": 0.49,
    "acc_b_total": 0.61,
    "acc_a_first": 0.54,
    "acc_a_second": 0.44,
    "acc_b_first": 0.54,
    "acc_b_second": 0.68,
    "diff_total": 0.12,
    "diff_second": 0.24
  },
  "window_acc_a": [
    0.7,
    0.5,
    0.6,
    0.4,
    0.5,
    0.4,
    0.3,
    0.4,
    0.8,
    0.3
  ],
  "window_acc_b": [
    0.5,
    0.5,
    0.4,
    0.9,
    0.4,
    0.7,
    0.8,
    0.7,
    0.5,
    0.7
  ],
  "final_weights": {
    "1->2": 0.0489,
    "2->1": 0.183,
    "2->3": 0.0489,
    "3->2": 0.183,
    "1->3": 0.4656,
    "3->1": 0.183
  },
  "results_a": [
    {
      "q": 1,
      "task_id": 30,
      "correct": true,
      "prediction": false,
      "label": false,
      "elapsed": 9.72
    },
    {
      "q": 2,
      "task_id": 88,
      "correct": false,
      "prediction": false,
      "label": true,
      "elapsed": 9.85
    },
    {
      "q": 3,
      "task_id": 92,
      "correct": true,
      "prediction": false,
      "label": false,
      "elapsed": 9.98
    },
    {
      "q": 4,
      "task_id": 36,
      "correct": true,
      "prediction": false,
      "label": false,
      "elapsed": 10.49
    },
    {
      "q": 5,
      "task_id": 63,
      "correct": false,
      "prediction": false,
      "label": true,
      "elapsed": 9.92
    },
    {
      "q": 6,
      "task_id": 71,
      "correct": true,
      "prediction": false,
      "label": false,
      "elapsed": 9.33
    },
    {
      "q": 7,
      "task_id": 34,
      "correct": true,
      "prediction": false,
      "label": false,
      "elapsed": 10.07
    },
    {
      "q": 8,
      "task_id": 81,
      "correct": false,
      "prediction": false,
      "label": true,
      "elapsed": 9.87
    },
    {
      "q": 9,
      "task_id": 95,
      "correct": true,
      "prediction": false,
      "label": false,
      "elapsed": 10.06
    },
    {
      "q": 10,
      "task_id": 62,
      "correct": true,
      "prediction": true,
      "label": true,
      "elapsed": 9.69
    },
    {
      "q": 11,
      "task_id": 70,
      "correct": true,
      "prediction": false,
      "label": false,
      "elapsed": 10.8
    },
    {
      "q": 12,
      "task_id": 28,
      "correct": false,
      "prediction": false,
      "label": true,
      "elapsed": 10.23
    },
    {
      "q": 13,
      "task_id": 69,
      "correct": false,
      "prediction": false,
      "label": true,
      "elapsed": 9.87
    },
    {
      "q": 14,
      "task_id": 33,
      "correct": true,
      "prediction": false,
      "label": false,
      "elapsed": 9.65
    },
    {
      "q": 15,
      "task_id": 64,
      "correct": false,
      "prediction": false,
      "label": true,
      "elapsed": 9.83
    },
    {
      "q": 16,
      "task_id": 8,
      "correct": false,
      "prediction": false,
      "label": true,
      "elapsed": 9.97
    },
    {
      "q": 17,
      "task_id": 93,
      "correct": false,
      "prediction": true,
      "label": false,
      "elapsed": 10.26
    },
    {
      "q": 18,
      "task_id": 32,
      "correct": true,
      "prediction": false,
      "label": false,
      "elapsed": 9.51
    },
    {
      "q": 19,
      "task_id": 99,
      "correct": true,
      "prediction": false,
      "label": false,
      "elapsed": 9.63
    },
    {
      "q": 20,
      "task_id": 16,
      "correct": true,
      "prediction": false,
      "label": false,
      "elapsed": 9.14
    },
    {
      "q": 21,
      "task_id": 58,
      "correct": true,
      "prediction": false,
      "label": false,
      "elapsed": 10.26
    },
    {
      "q": 22,
      "task_id": 31,
      "correct": true,
      "prediction": false,
      "label": false,
      "elapsed": 10.36
    },
    {
      "q": 23,
      "task_id": 45,
      "correct": false,
      "prediction": false,
      "label": true,
      "elapsed": 9.96
    },
    {
      "q": 24,
      "task_id": 98,
      "correct": true,
      "prediction": false,
      "label": false,
      "elapsed": 8.98
    },
    {
      "q": 25,
      "task_id": 50,
      "correct": true,
      "prediction": false,
      "label": false,
      "elapsed": 9.73
    },
    {
      "q": 26,
      "task_id": 25,
      "correct": false,
      "prediction": false,
      "label": true,
      "elapsed": 10.18
    },
    {
      "q": 27,
      "task_id": 83,
      "correct": false,
      "prediction": false,
      "label": true,
      "elapsed": 10.05
    },
    {
      "q": 28,
      "task_id": 59,
      "correct": true,
      "prediction": false,
      "label": false,
      "elapsed": 10.01
    },
    {
      "q": 29,
      "task_id": 68,
      "correct": false,
      "prediction": false,
      "label": true,
      "elapsed": 9.18
    },
    {
      "q": 30,
      "task_id": 53,
      "correct": true,
      "prediction": false,
      "label": false,
      "elapsed": 10.28
    },
    {
      "q": 31,
      "task_id": 79,
      "correct": true,
      "prediction": false,
      "label": false,
      "elapsed": 9.51
    },
    {
      "q": 32,
      "task_id": 72,
      "correct": true,
      "prediction": false,
      "label": false,
      "elapsed": 10.21
    },
    {
      "q": 33,
      "task_id": 40,
      "correct": false,
      "prediction": false,
      "label": true,
      "elapsed": 10.13
    },
    {
      "q": 34,
      "task_id": 96,
      "correct": true,
      "prediction": false,
      "label": false,
      "elapsed": 9.32
    },
    {
      "q": 35,
      "task_id": 6,
      "correct": false,
      "prediction": false,
      "label": true,
      "elapsed": 9.51
    },
    {
      "q": 36,
      "task_id": 24,
      "correct": true,
      "prediction": true,
      "label": true,
      "elapsed": 9.65
    },
    {
      "q": 37,
      "task_id": 75,
      "correct": false,
      "prediction": true,
      "label": false,
      "elapsed": 10.58
    },
    {
      "q": 38,
      "task_id": 3,
      "correct": false,
      "prediction": false,
      "label": true,
      "elapsed": 9.49
    },
    {
      "q": 39,
      "task_id": 27,
      "correct": false,
      "prediction": false,
      "label": true,
      "elapsed": 10.13
    },
    {
      "q": 40,
      "task_id": 80,
      "correct": false,
      "prediction": false,
      "label": true,
      "elapsed": 9.65
    },
    {
      "q": 41,
      "task_id": 76,
      "correct": true,
      "prediction": false,
      "label": false,
      "elapsed": 9.55
    },
    {
      "q": 42,
      "task_id": 39,
      "correct": true,
      "prediction": false,
      "label": false,
      "elapsed": 9.99
    },
    {
      "q": 43,
      "task_id": 54,
      "correct": true,
      "prediction": false,
      "label": false,
      "elapsed": 10.18
    },
    {
      "q": 44,
      "task_id": 22,
      "correct": true,
      "prediction": true,
      "label": true,
      "elapsed": 10.12
    },
    {
      "q": 45,
      "task_id": 21,
      "correct": false,
      "prediction": false,
      "label": true,
      "elapsed": 10.39
    },
    {
      "q": 46,
      "task_id": 9,
      "correct": false,
      "prediction": false,
      "label": true,
      "elapsed": 9.05
    },
    {
      "q": 47,
      "task_id": 15,
      "correct": false,
      "prediction": true,
      "label": false,
      "elapsed": 9.39
    },
    {
      "q": 48,
      "task_id": 48,
      "correct": false,
      "prediction": false,
      "label": true,
      "elapsed": 9.78
    },
    {
      "q": 49,
      "task_id": 51,
      "correct": true,
      "prediction": false,
      "label": false,
      "elapsed": 10.39
    },
    {
      "q": 50,
      "task_id": 26,
      "correct": false,
      "prediction": false,
      "label": true,
      "elapsed": 9.36
    },
    {
      "q": 51,
      "task_id": 78,
      "correct": true,
      "prediction": false,
      "label": false,
      "elapsed": 9.41
    },
    {
      "q": 52,
      "task_id": 1,
      "correct": false,
      "prediction": false,
      "label": true,
      "elapsed": 9.69
    },
    {
      "q": 53,
      "task_id": 35,
      "correct": true,
      "prediction": false,
      "label": false,
      "elapsed": 10.71
    },
    {
      "q": 54,
      "task_id": 43,
      "correct": false,
      "prediction": false,
      "label": true,
      "elapsed": 10.41
    },
    {
      "q": 55,
      "task_id": 29,
      "correct": false,
      "prediction": false,
      "label": true,
      "elapsed": 9.71
    },
    {
      "q": 56,
      "task_id": 7,
      "correct": false,
      "prediction": false,
      "label": true,
      "elapsed": 9.37
    },
    {
      "q": 57,
      "task_id": 37,
      "correct": true,
      "prediction": false,
      "label": false,
      "elapsed": 10.25
    },
    {
      "q": 58,
      "task_id": 84,
      "correct": false,
      "prediction": false,
      "label": true,
      "elapsed": 10.65
    },
    {
      "q": 59,
      "task_id": 14,
      "correct": true,
      "prediction": false,
      "label": false,
      "elapsed": 9.69
    },
    {
      "q": 60,
      "task_id": 5,
      "correct": false,
      "prediction": false,
      "label": true,
      "elapsed": 9.44
    },
    {
      "q": 61,
      "task_id": 82,
      "correct": false,
      "prediction": false,
      "label": true,
      "elapsed": 9.63
    },
    {
      "q": 62,
      "task_id": 73,
      "correct": true,
      "prediction": false,
      "label": false,
      "elapsed": 9.44
    },
    {
      "q": 63,
      "task_id": 18,
      "correct": false,
      "prediction": true,
      "label": false,
      "elapsed": 9.46
    },
    {
      "q": 64,
      "task_id": 86,
      "correct": false,
      "prediction": false,
      "label": true,
      "elapsed": 9.53
    },
    {
      "q": 65,
      "task_id": 20,
      "correct": false,
      "prediction": false,
      "label": true,
      "elapsed": 9.5
    },
    {
      "q": 66,
      "task_id": 87,
      "correct": false,
      "prediction": false,
      "label": true,
      "elapsed": 10.06
    },
    {
      "q": 67,
      "task_id": 23,
      "correct": false,
      "prediction": false,
      "label": true,
      "elapsed": 11.37
    },
    {
      "q": 68,
      "task_id": 38,
      "correct": true,
      "prediction": false,
      "label": false,
      "elapsed": 10.12
    },
    {
      "q": 69,
      "task_id": 90,
      "correct": true,
      "prediction": false,
      "label": false,
      "elapsed": 10.38
    },
    {
      "q": 70,
      "task_id": 0,
      "correct": false,
      "prediction": false,
      "label": true,
      "elapsed": 9.21
    },
    {
      "q": 71,
      "task_id": 42,
      "correct": false,
      "prediction": false,
      "label": true,
      "elapsed": 9.73
    },
    {
      "q": 72,
      "task_id": 91,
      "correct": true,
      "prediction": false,
      "label": false,
      "elapsed": 9.63
    },
    {
      "q": 73,
      "task_id": 85,
      "correct": false,
      "prediction": false,
      "label": true,
      "elapsed": 9.63
    },
    {
      "q": 74,
      "task_id": 74,
      "correct": false,
      "prediction": true,
      "label": false,
      "elapsed": 9.36
    },
    {
      "q": 75,
      "task_id": 10,
      "correct": true,
      "prediction": false,
      "label": false,
      "elapsed": 9.25
    },
    {
      "q": 76,
      "task_id": 4,
      "correct": false,
      "prediction": false,
      "label": true,
      "elapsed": 9.26
    },
    {
      "q": 77,
      "task_id": 11,
      "correct": true,
      "prediction": false,
      "label": false,
      "elapsed": 10.24
    },
    {
      "q": 78,
      "task_id": 77,
      "correct": true,
      "prediction": false,
      "label": false,
      "elapsed": 9.22
    },
    {
      "q": 79,
      "task_id": 44,
      "correct": false,
      "prediction": false,
      "label": true,
      "elapsed": 9.69
    },
    {
      "q": 80,
      "task_id": 67,
      "correct": false,
      "prediction": false,
      "label": true,
      "elapsed": 9.66
    },
    {
      "q": 81,
      "task_id": 57,
      "correct": true,
      "prediction": false,
      "label": false,
      "elapsed": 9.86
    },
    {
      "q": 82,
      "task_id": 60,
      "correct": false,
      "prediction": false,
      "label": true,
      "elapsed": 9.35
    },
    {
      "q": 83,
      "task_id": 55,
      "correct": true,
      "prediction": false,
      "label": false,
      "elapsed": 9.54
    },
    {
      "q": 84,
      "task_id": 19,
      "correct": true,
      "prediction": false,
      "label": false,
      "elapsed": 9.53
    },
    {
      "q": 85,
      "task_id": 52,
      "correct": true,
      "prediction": false,
      "label": false,
      "elapsed": 9.73
    },
    {
      "q": 86,
      "task_id": 13,
      "correct": true,
      "prediction": false,
      "label": false,
      "elapsed": 9.62
    },
    {
      "q": 87,
      "task_id": 89,
      "correct": false,
      "prediction": false,
      "label": true,
      "elapsed": 10.01
    },
    {
      "q": 88,
      "task_id": 17,
      "correct": true,
      "prediction": false,
      "label": false,
      "elapsed": 9.69
    },
    {
      "q": 89,
      "task_id": 94,
      "correct": true,
      "prediction": false,
      "label": false,
      "elapsed": 9.82
    },
    {
      "q": 90,
      "task_id": 97,
      "correct": true,
      "prediction": false,
      "label": false,
      "elapsed": 9.8
    },
    {
      "q": 91,
      "task_id": 47,
      "correct": false,
      "prediction": false,
      "label": true,
      "elapsed": 10.27
    },
    {
      "q": 92,
      "task_id": 46,
      "correct": false,
      "prediction": false,
      "label": true,
      "elapsed": 9.17
    },
    {
      "q": 93,
      "task_id": 65,
      "correct": false,
      "prediction": false,
      "label": true,
      "elapsed": 9.7
    },
    {
      "q": 94,
      "task_id": 56,
      "correct": true,
      "prediction": false,
      "label": false,
      "elapsed": 10.31
    },
    {
      "q": 95,
      "task_id": 12,
      "correct": true,
      "prediction": false,
      "label": false,
      "elapsed": 9.6
    },
    {
      "q": 96,
      "task_id": 66,
      "correct": false,
      "prediction": false,
      "label": true,
      "elapsed": 10.17
    },
    {
      "q": 97,
      "task_id": 41,
      "correct": true,
      "prediction": true,
      "label": true,
      "elapsed": 10.27
    },
    {
      "q": 98,
      "task_id": 49,
      "correct": false,
      "prediction": false,
      "label": true,
      "elapsed": 9.71
    },
    {
      "q": 99,
      "task_id": 61,
      "correct": false,
      "prediction": false,
      "label": true,
      "elapsed": 10.37
    },
    {
      "q": 100,
      "task_id": 2,
      "correct": false,
      "prediction": false,
      "label": true,
      "elapsed": 9.69
    }
  ],
  "results_b": [
    {
      "q": 1,
      "task_id": 30,
      "correct": true,
      "prediction": false,
      "label": false,
      "elapsed": 10.8,
      "path_used": [
        [
          1,
          2
        ],
        [
          2,
          3
        ]
      ],
      "used_feedback": false,
      "weights": {
        "1->2": 0.55,
        "2->1": 0.495,
        "2->3": 0.55,
        "3->2": 0.495,
        "1->3": 0.495,
        "3->1": 0.495
      }
    },
    {
      "q": 2,
      "task_id": 88,
      "correct": false,
      "prediction": false,
      "label": true,
      "elapsed": 11.35,
      "path_used": [
        [
          1,
          2
        ],
        [
          2,
          3
        ]
      ],
      "used_feedback": false,
      "weights": {
        "1->2": 0.385,
        "2->1": 0.49,
        "2->3": 0.385,
        "3->2": 0.49,
        "1->3": 0.49,
        "3->1": 0.49
      }
    },
    {
      "q": 3,
      "task_id": 92,
      "correct": true,
      "prediction": false,
      "label": false,
      "elapsed": 6.88,
      "path_used": [
        [
          1,
          3
        ]
      ],
      "used_feedback": false,
      "weights": {
        "1->2": 0.3811,
        "2->1": 0.4851,
        "2->3": 0.3811,
        "3->2": 0.4851,
        "1->3": 0.541,
        "3->1": 0.4851
      }
    },
    {
      "q": 4,
      "task_id": 36,
      "correct": false,
      "prediction": true,
      "label": false,
      "elapsed": 7.32,
      "path_used": [
        [
          1,
          3
        ]
      ],
      "used_feedback": false,
      "weights": {
        "1->2": 0.3773,
        "2->1": 0.4803,
        "2->3": 0.3773,
        "3->2": 0.4803,
        "1->3": 0.3787,
        "3->1": 0.4803
      }
    },
    {
      "q": 5,
      "task_id": 63,
      "correct": true,
      "prediction": true,
      "label": true,
      "elapsed": 6.2,
      "path_used": [
        [
          1,
          3
        ]
      ],
      "used_feedback": false,
      "weights": {
        "1->2": 0.3736,
        "2->1": 0.4755,
        "2->3": 0.3736,
        "3->2": 0.4755,
        "1->3": 0.4409,
        "3->1": 0.4755
      }
    },
    {
      "q": 6,
      "task_id": 71,
      "correct": true,
      "prediction": false,
      "label": false,
      "elapsed": 6.99,
      "path_used": [
        [
          1,
          3
        ]
      ],
      "used_feedback": false,
      "weights": {
        "1->2": 0.3698,
        "2->1": 0.4707,
        "2->3": 0.3698,
        "3->2": 0.4707,
        "1->3": 0.4968,
        "3->1": 0.4707
      }
    },
    {
      "q": 7,
      "task_id": 34,
      "correct": true,
      "prediction": false,
      "label": false,
      "elapsed": 7.98,
      "path_used": [
        [
          1,
          3
        ]
      ],
      "used_feedback": false,
      "weights": {
        "1->2": 0.3661,
        "2->1": 0.466,
        "2->3": 0.3661,
        "3->2": 0.466,
        "1->3": 0.5471,
        "3->1": 0.466
      }
    },
    {
      "q": 8,
      "task_id": 81,
      "correct": false,
      "prediction": false,
      "label": true,
      "elapsed": 6.66,
      "path_used": [
        [
          1,
          3
        ]
      ],
      "used_feedback": false,
      "weights": {
        "1->2": 0.3625,
        "2->1": 0.4614,
        "2->3": 0.3625,
        "3->2": 0.4614,
        "1->3": 0.383,
        "3->1": 0.4614
      }
    },
    {
      "q": 9,
      "task_id": 95,
      "correct": false,
      "prediction": true,
      "label": false,
      "elapsed": 7.1,
      "path_used": [
        [
          1,
          3
        ]
      ],
      "used_feedback": false,
      "weights": {
        "1->2": 0.3588,
        "2->1": 0.4568,
        "2->3": 0.3588,
        "3->2": 0.4568,
        "1->3": 0.2681,
        "3->1": 0.4568
      }
    },
    {
      "q": 10,
      "task_id": 62,
      "correct": false,
      "prediction": false,
      "label": true,
      "elapsed": 9.65,
      "path_used": [
        [
          1,
          2
        ],
        [
          2,
          3
        ]
      ],
      "used_feedback": false,
      "weights": {
        "1->2": 0.2512,
        "2->1": 0.4522,
        "2->3": 0.2512,
        "3->2": 0.4522,
        "1->3": 0.2654,
        "3->1": 0.4522
      }
    },
    {
      "q": 11,
      "task_id": 70,
      "correct": false,
      "prediction": true,
      "label": false,
      "elapsed": 6.41,
      "path_used": [
        [
          1,
          3
        ]
      ],
      "used_feedback": false,
      "weights": {
        "1->2": 0.2487,
        "2->1": 0.4477,
        "2->3": 0.2487,
        "3->2": 0.4477,
        "1->3": 0.1858,
        "3->1": 0.4477
      }
    },
    {
      "q": 12,
      "task_id": 28,
      "correct": false,
      "prediction": false,
      "label": true,
      "elapsed": 10.79,
      "path_used": [
        [
          1,
          2
        ],
        [
          2,
          3
        ]
      ],
      "used_feedback": false,
      "weights": {
        "1->2": 0.1741,
        "2->1": 0.4432,
        "2->3": 0.1741,
        "3->2": 0.4432,
        "1->3": 0.1839,
        "3->1": 0.4432
      }
    },
    {
      "q": 13,
      "task_id": 69,
      "correct": false,
      "prediction": false,
      "label": true,
      "elapsed": 7.09,
      "path_used": [
        [
          1,
          3
        ]
      ],
      "used_feedback": false,
      "weights": {
        "1->2": 0.1723,
        "2->1": 0.4388,
        "2->3": 0.1723,
        "3->2": 0.4388,
        "1->3": 0.1287,
        "3->1": 0.4388
      }
    },
    {
      "q": 14,
      "task_id": 33,
      "correct": true,
      "prediction": false,
      "label": false,
      "elapsed": 10.21,
      "path_used": [
        [
          1,
          2
        ],
        [
          2,
          3
        ]
      ],
      "used_feedback": false,
      "weights": {
        "1->2": 0.2551,
        "2->1": 0.4344,
        "2->3": 0.2551,
        "3->2": 0.4344,
        "1->3": 0.1275,
        "3->1": 0.4344
      }
    },
    {
      "q": 15,
      "task_id": 64,
      "correct": false,
      "prediction": false,
      "label": true,
      "elapsed": 9.38,
      "path_used": [
        [
          1,
          2
        ],
        [
          2,
          3
        ]
      ],
      "used_feedback": false,
      "weights": {
        "1->2": 0.1786,
        "2->1": 0.43,
        "2->3": 0.1786,
        "3->2": 0.43,
        "1->3": 0.1262,
        "3->1": 0.43
      }
    },
    {
      "q": 16,
      "task_id": 8,
      "correct": true,
      "prediction": true,
      "label": true,
      "elapsed": 10.12,
      "path_used": [
        [
          1,
          2
        ],
        [
          2,
          3
        ]
      ],
      "used_feedback": false,
      "weights": {
        "1->2": 0.2607,
        "2->1": 0.4257,
        "2->3": 0.2607,
        "3->2": 0.4257,
        "1->3": 0.1249,
        "3->1": 0.4257
      }
    },
    {
      "q": 17,
      "task_id": 93,
      "correct": false,
      "prediction": true,
      "label": false,
      "elapsed": 10.79,
      "path_used": [
        [
          1,
          2
        ],
        [
          2,
          3
        ]
      ],
      "used_feedback": false,
      "weights": {
        "1->2": 0.1825,
        "2->1": 0.4215,
        "2->3": 0.1825,
        "3->2": 0.4215,
        "1->3": 0.1237,
        "3->1": 0.4215
      }
    },
    {
      "q": 18,
      "task_id": 32,
      "correct": true,
      "prediction": false,
      "label": false,
      "elapsed": 10.46,
      "path_used": [
        [
          1,
          2
        ],
        [
          2,
          3
        ]
      ],
      "used_feedback": false,
      "weights": {
        "1->2": 0.2642,
        "2->1": 0.4173,
        "2->3": 0.2642,
        "3->2": 0.4173,
        "1->3": 0.1224,
        "3->1": 0.4173
      }
    },
    {
      "q": 19,
      "task_id": 99,
      "correct": true,
      "prediction": false,
      "label": false,
      "elapsed": 10.07,
      "path_used": [
        [
          1,
          2
        ],
        [
          2,
          3
        ]
      ],
      "used_feedback": false,
      "weights": {
        "1->2": 0.3378,
        "2->1": 0.4131,
        "2->3": 0.3378,
        "3->2": 0.4131,
        "1->3": 0.1212,
        "3->1": 0.4131
      }
    },
    {
      "q": 20,
      "task_id": 16,
      "correct": true,
      "prediction": false,
      "label": false,
      "elapsed": 10.81,
      "path_used": [
        [
          1,
          2
        ],
        [
          2,
          3
        ]
      ],
      "used_feedback": false,
      "weights": {
        "1->2": 0.404,
        "2->1": 0.409,
        "2->3": 0.404,
        "3->2": 0.409,
        "1->3": 0.12,
        "3->1": 0.409
      }
    },
    {
      "q": 21,
      "task_id": 58,
      "correct": true,
      "prediction": false,
      "label": false,
      "elapsed": 10.66,
      "path_used": [
        [
          1,
          2
        ],
        [
          2,
          3
        ]
      ],
      "used_feedback": false,
      "weights": {
        "1->2": 0.4636,
        "2->1": 0.4049,
        "2->3": 0.4636,
        "3->2": 0.4049,
        "1->3": 0.1188,
        "3->1": 0.4049
      }
    },
    {
      "q": 22,
      "task_id": 31,
      "correct": true,
      "prediction": false,
      "label": false,
      "elapsed": 10.09,
      "path_used": [
        [
          1,
          2
        ],
        [
          2,
          3
        ]
      ],
      "used_feedback": false,
      "weights": {
        "1->2": 0.5173,
        "2->1": 0.4008,
        "2->3": 0.5173,
        "3->2": 0.4008,
        "1->3": 0.1176,
        "3->1": 0.4008
      }
    },
    {
      "q": 23,
      "task_id": 45,
      "correct": false,
      "prediction": false,
      "label": true,
      "elapsed": 10.2,
      "path_used": [
        [
          1,
          2
        ],
        [
          2,
          3
        ]
      ],
      "used_feedback": false,
      "weights": {
        "1->2": 0.3621,
        "2->1": 0.3968,
        "2->3": 0.3621,
        "3->2": 0.3968,
        "1->3": 0.1164,
        "3->1": 0.3968
      }
    },
    {
      "q": 24,
      "task_id": 98,
      "correct": true,
      "prediction": false,
      "label": false,
      "elapsed": 9.97,
      "path_used": [
        [
          1,
          2
        ],
        [
          2,
          3
        ]
      ],
      "used_feedback": false,
      "weights": {
        "1->2": 0.4259,
        "2->1": 0.3928,
        "2->3": 0.4259,
        "3->2": 0.3928,
        "1->3": 0.1153,
        "3->1": 0.3928
      }
    },
    {
      "q": 25,
      "task_id": 50,
      "correct": false,
      "prediction": true,
      "label": false,
      "elapsed": 9.68,
      "path_used": [
        [
          1,
          2
        ],
        [
          2,
          3
        ]
      ],
      "used_feedback": false,
      "weights": {
        "1->2": 0.2981,
        "2->1": 0.3889,
        "2->3": 0.2981,
        "3->2": 0.3889,
        "1->3": 0.1141,
        "3->1": 0.3889
      }
    },
    {
      "q": 26,
      "task_id": 25,
      "correct": false,
      "prediction": false,
      "label": true,
      "elapsed": 9.61,
      "path_used": [
        [
          1,
          2
        ],
        [
          2,
          3
        ]
      ],
      "used_feedback": false,
      "weights": {
        "1->2": 0.2087,
        "2->1": 0.385,
        "2->3": 0.2087,
        "3->2": 0.385,
        "1->3": 0.113,
        "3->1": 0.385
      }
    },
    {
      "q": 27,
      "task_id": 83,
      "correct": true,
      "prediction": true,
      "label": true,
      "elapsed": 10.1,
      "path_used": [
        [
          1,
          2
        ],
        [
          2,
          3
        ]
      ],
      "used_feedback": false,
      "weights": {
        "1->2": 0.2878,
        "2->1": 0.3812,
        "2->3": 0.2878,
        "3->2": 0.3812,
        "1->3": 0.1118,
        "3->1": 0.3812
      }
    },
    {
      "q": 28,
      "task_id": 59,
      "correct": false,
      "prediction": true,
      "label": false,
      "elapsed": 10.04,
      "path_used": [
        [
          1,
          2
        ],
        [
          2,
          3
        ]
      ],
      "used_feedback": false,
      "weights": {
        "1->2": 0.2015,
        "2->1": 0.3774,
        "2->3": 0.2015,
        "3->2": 0.3774,
        "1->3": 0.1107,
        "3->1": 0.3774
      }
    },
    {
      "q": 29,
      "task_id": 68,
      "correct": false,
      "prediction": false,
      "label": true,
      "elapsed": 10.59,
      "path_used": [
        [
          1,
          2
        ],
        [
          2,
          3
        ]
      ],
      "used_feedback": false,
      "weights": {
        "1->2": 0.141,
        "2->1": 0.3736,
        "2->3": 0.141,
        "3->2": 0.3736,
        "1->3": 0.1096,
        "3->1": 0.3736
      }
    },
    {
      "q": 30,
      "task_id": 53,
      "correct": false,
      "prediction": true,
      "label": false,
      "elapsed": 10.11,
      "path_used": [
        [
          1,
          2
        ],
        [
          2,
          3
        ]
      ],
      "used_feedback": false,
      "weights": {
        "1->2": 0.0987,
        "2->1": 0.3699,
        "2->3": 0.0987,
        "3->2": 0.3699,
        "1->3": 0.1085,
        "3->1": 0.3699
      }
    },
    {
      "q": 31,
      "task_id": 79,
      "correct": true,
      "prediction": false,
      "label": false,
      "elapsed": 6.76,
      "path_used": [
        [
          1,
          3
        ]
      ],
      "used_feedback": false,
      "weights": {
        "1->2": 0.0977,
        "2->1": 0.3662,
        "2->3": 0.0977,
        "3->2": 0.3662,
        "1->3": 0.1977,
        "3->1": 0.3662
      }
    },
    {
      "q": 32,
      "task_id": 72,
      "correct": true,
      "prediction": false,
      "label": false,
      "elapsed": 6.64,
      "path_used": [
        [
          1,
          3
        ]
      ],
      "used_feedback": false,
      "weights": {
        "1->2": 0.0968,
        "2->1": 0.3625,
        "2->3": 0.0968,
        "3->2": 0.3625,
        "1->3": 0.2779,
        "3->1": 0.3625
      }
    },
    {
      "q": 33,
      "task_id": 40,
      "correct": true,
      "prediction": true,
      "label": true,
      "elapsed": 6.79,
      "path_used": [
        [
          1,
          3
        ]
      ],
      "used_feedback": false,
      "weights": {
        "1->2": 0.0958,
        "2->1": 0.3589,
        "2->3": 0.0958,
        "3->2": 0.3589,
        "1->3": 0.3501,
        "3->1": 0.3589
      }
    },
    {
      "q": 34,
      "task_id": 96,
      "correct": true,
      "prediction": false,
      "label": false,
      "elapsed": 6.84,
      "path_used": [
        [
          1,
          3
        ]
      ],
      "used_feedback": false,
      "weights": {
        "1->2": 0.0948,
        "2->1": 0.3553,
        "2->3": 0.0948,
        "3->2": 0.3553,
        "1->3": 0.4151,
        "3->1": 0.3553
      }
    },
    {
      "q": 35,
      "task_id": 6,
      "correct": true,
      "prediction": true,
      "label": true,
      "elapsed": 6.92,
      "path_used": [
        [
          1,
          3
        ]
      ],
      "used_feedback": false,
      "weights": {
        "1->2": 0.0939,
        "2->1": 0.3517,
        "2->3": 0.0939,
        "3->2": 0.3517,
        "1->3": 0.4736,
        "3->1": 0.3517
      }
    },
    {
      "q": 36,
      "task_id": 24,
      "correct": false,
      "prediction": false,
      "label": true,
      "elapsed": 6.49,
      "path_used": [
        [
          1,
          3
        ]
      ],
      "used_feedback": false,
      "weights": {
        "1->2": 0.0929,
        "2->1": 0.3482,
        "2->3": 0.0929,
        "3->2": 0.3482,
        "1->3": 0.3315,
        "3->1": 0.3482
      }
    },
    {
      "q": 37,
      "task_id": 75,
      "correct": true,
      "prediction": false,
      "label": false,
      "elapsed": 7.16,
      "path_used": [
        [
          1,
          3
        ]
      ],
      "used_feedback": false,
      "weights": {
        "1->2": 0.092,
        "2->1": 0.3447,
        "2->3": 0.092,
        "3->2": 0.3447,
        "1->3": 0.3984,
        "3->1": 0.3447
      }
    },
    {
      "q": 38,
      "task_id": 3,
      "correct": true,
      "prediction": true,
      "label": true,
      "elapsed": 7.46,
      "path_used": [
        [
          1,
          3
        ]
      ],
      "used_feedback": false,
      "weights": {
        "1->2": 0.0911,
        "2->1": 0.3413,
        "2->3": 0.0911,
        "3->2": 0.3413,
        "1->3": 0.4585,
        "3->1": 0.3413
      }
    },
    {
      "q": 39,
      "task_id": 27,
      "correct": true,
      "prediction": true,
      "label": true,
      "elapsed": 6.95,
      "path_used": [
        [
          1,
          3
        ]
      ],
      "used_feedback": false,
      "weights": {
        "1->2": 0.0902,
        "2->1": 0.3379,
        "2->3": 0.0902,
        "3->2": 0.3379,
        "1->3": 0.5127,
        "3->1": 0.3379
      }
    },
    {
      "q": 40,
      "task_id": 80,
      "correct": true,
      "prediction": true,
      "label": true,
      "elapsed": 6.58,
      "path_used": [
        [
          1,
          3
        ]
      ],
      "used_feedback": false,
      "weights": {
        "1->2": 0.0893,
        "2->1": 0.3345,
        "2->3": 0.0893,
        "3->2": 0.3345,
        "1->3": 0.5614,
        "3->1": 0.3345
      }
    },
    {
      "q": 41,
      "task_id": 76,
      "correct": false,
      "prediction": true,
      "label": false,
      "elapsed": 7.14,
      "path_used": [
        [
          1,
          3
        ]
      ],
      "used_feedback": false,
      "weights": {
        "1->2": 0.0884,
        "2->1": 0.3311,
        "2->3": 0.0884,
        "3->2": 0.3311,
        "1->3": 0.393,
        "3->1": 0.3311
      }
    },
    {
      "q": 42,
      "task_id": 39,
      "correct": false,
      "prediction": true,
      "label": false,
      "elapsed": 6.73,
      "path_used": [
        [
          1,
          3
        ]
      ],
      "used_feedback": false,
      "weights": {
        "1->2": 0.0875,
        "2->1": 0.3278,
        "2->3": 0.0875,
        "3->2": 0.3278,
        "1->3": 0.2751,
        "3->1": 0.3278
      }
    },
    {
      "q": 43,
      "task_id": 54,
      "correct": true,
      "prediction": false,
      "label": false,
      "elapsed": 7.08,
      "path_used": [
        [
          1,
          3
        ]
      ],
      "used_feedback": false,
      "weights": {
        "1->2": 0.0866,
        "2->1": 0.3246,
        "2->3": 0.0866,
        "3->2": 0.3246,
        "1->3": 0.3476,
        "3->1": 0.3246
      }
    },
    {
      "q": 44,
      "task_id": 22,
      "correct": false,
      "prediction": false,
      "label": true,
      "elapsed": 7.05,
      "path_used": [
        [
          1,
          3
        ]
      ],
      "used_feedback": false,
      "weights": {
        "1->2": 0.0858,
        "2->1": 0.3213,
        "2->3": 0.0858,
        "3->2": 0.3213,
        "1->3": 0.2433,
        "3->1": 0.3213
      }
    },
    {
      "q": 45,
      "task_id": 21,
      "correct": false,
      "prediction": false,
      "label": true,
      "elapsed": 6.92,
      "path_used": [
        [
          1,
          3
        ]
      ],
      "used_feedback": false,
      "weights": {
        "1->2": 0.0849,
        "2->1": 0.3181,
        "2->3": 0.0849,
        "3->2": 0.3181,
        "1->3": 0.1703,
        "3->1": 0.3181
      }
    },
    {
      "q": 46,
      "task_id": 9,
      "correct": true,
      "prediction": true,
      "label": true,
      "elapsed": 6.87,
      "path_used": [
        [
          1,
          3
        ]
      ],
      "used_feedback": false,
      "weights": {
        "1->2": 0.0841,
        "2->1": 0.3149,
        "2->3": 0.0841,
        "3->2": 0.3149,
        "1->3": 0.2533,
        "3->1": 0.3149
      }
    },
    {
      "q": 47,
      "task_id": 15,
      "correct": true,
      "prediction": false,
      "label": false,
      "elapsed": 6.83,
      "path_used": [
        [
          1,
          3
        ]
      ],
      "used_feedback": false,
      "weights": {
        "1->2": 0.0832,
        "2->1": 0.3118,
        "2->3": 0.0832,
        "3->2": 0.3118,
        "1->3": 0.328,
        "3->1": 0.3118
      }
    },
    {
      "q": 48,
      "task_id": 48,
      "correct": false,
      "prediction": false,
      "label": true,
      "elapsed": 6.32,
      "path_used": [
        [
          1,
          3
        ]
      ],
      "used_feedback": false,
      "weights": {
        "1->2": 0.0824,
        "2->1": 0.3086,
        "2->3": 0.0824,
        "3->2": 0.3086,
        "1->3": 0.2296,
        "3->1": 0.3086
      }
    },
    {
      "q": 49,
      "task_id": 51,
      "correct": true,
      "prediction": false,
      "label": false,
      "elapsed": 7.08,
      "path_used": [
        [
          1,
          3
        ]
      ],
      "used_feedback": false,
      "weights": {
        "1->2": 0.0816,
        "2->1": 0.3056,
        "2->3": 0.0816,
        "3->2": 0.3056,
        "1->3": 0.3066,
        "3->1": 0.3056
      }
    },
    {
      "q": 50,
      "task_id": 26,
      "correct": false,
      "prediction": false,
      "label": true,
      "elapsed": 6.8,
      "path_used": [
        [
          1,
          3
        ]
      ],
      "used_feedback": false,
      "weights": {
        "1->2": 0.0807,
        "2->1": 0.3025,
        "2->3": 0.0807,
        "3->2": 0.3025,
        "1->3": 0.2146,
        "3->1": 0.3025
      }
    },
    {
      "q": 51,
      "task_id": 78,
      "correct": true,
      "prediction": false,
      "label": false,
      "elapsed": 6.69,
      "path_used": [
        [
          1,
          3
        ]
      ],
      "used_feedback": false,
      "weights": {
        "1->2": 0.0799,
        "2->1": 0.2995,
        "2->3": 0.0799,
        "3->2": 0.2995,
        "1->3": 0.2932,
        "3->1": 0.2995
      }
    },
    {
      "q": 52,
      "task_id": 1,
      "correct": true,
      "prediction": true,
      "label": true,
      "elapsed": 6.34,
      "path_used": [
        [
          1,
          3
        ]
      ],
      "used_feedback": false,
      "weights": {
        "1->2": 0.0791,
        "2->1": 0.2965,
        "2->3": 0.0791,
        "3->2": 0.2965,
        "1->3": 0.3638,
        "3->1": 0.2965
      }
    },
    {
      "q": 53,
      "task_id": 35,
      "correct": false,
      "prediction": true,
      "label": false,
      "elapsed": 6.71,
      "path_used": [
        [
          1,
          3
        ]
      ],
      "used_feedback": false,
      "weights": {
        "1->2": 0.0783,
        "2->1": 0.2935,
        "2->3": 0.0783,
        "3->2": 0.2935,
        "1->3": 0.2547,
        "3->1": 0.2935
      }
    },
    {
      "q": 54,
      "task_id": 43,
      "correct": false,
      "prediction": false,
      "label": true,
      "elapsed": 7.1,
      "path_used": [
        [
          1,
          3
        ]
      ],
      "used_feedback": false,
      "weights": {
        "1->2": 0.0776,
        "2->1": 0.2906,
        "2->3": 0.0776,
        "3->2": 0.2906,
        "1->3": 0.1783,
        "3->1": 0.2906
      }
    },
    {
      "q": 55,
      "task_id": 29,
      "correct": false,
      "prediction": false,
      "label": true,
      "elapsed": 6.74,
      "path_used": [
        [
          1,
          3
        ]
      ],
      "used_feedback": false,
      "weights": {
        "1->2": 0.0768,
        "2->1": 0.2877,
        "2->3": 0.0768,
        "3->2": 0.2877,
        "1->3": 0.1248,
        "3->1": 0.2877
      }
    },
    {
      "q": 56,
      "task_id": 7,
      "correct": true,
      "prediction": true,
      "label": true,
      "elapsed": 6.37,
      "path_used": [
        [
          1,
          3
        ]
      ],
      "used_feedback": false,
      "weights": {
        "1->2": 0.076,
        "2->1": 0.2848,
        "2->3": 0.076,
        "3->2": 0.2848,
        "1->3": 0.2123,
        "3->1": 0.2848
      }
    },
    {
      "q": 57,
      "task_id": 37,
      "correct": true,
      "prediction": false,
      "label": false,
      "elapsed": 7.17,
      "path_used": [
        [
          1,
          3
        ]
      ],
      "used_feedback": false,
      "weights": {
        "1->2": 0.0753,
        "2->1": 0.282,
        "2->3": 0.0753,
        "3->2": 0.282,
        "1->3": 0.2911,
        "3->1": 0.282
      }
    },
    {
      "q": 58,
      "task_id": 84,
      "correct": true,
      "prediction": true,
      "label": true,
      "elapsed": 7.77,
      "path_used": [
        [
          1,
          3
        ]
      ],
      "used_feedback": false,
      "weights": {
        "1->2": 0.0745,
        "2->1": 0.2791,
        "2->3": 0.0745,
        "3->2": 0.2791,
        "1->3": 0.362,
        "3->1": 0.2791
      }
    },
    {
      "q": 59,
      "task_id": 14,
      "correct": true,
      "prediction": false,
      "label": false,
      "elapsed": 6.33,
      "path_used": [
        [
          1,
          3
        ]
      ],
      "used_feedback": false,
      "weights": {
        "1->2": 0.0738,
        "2->1": 0.2763,
        "2->3": 0.0738,
        "3->2": 0.2763,
        "1->3": 0.4258,
        "3->1": 0.2763
      }
    },
    {
      "q": 60,
      "task_id": 5,
      "correct": true,
      "prediction": true,
      "label": true,
      "elapsed": 7.16,
      "path_used": [
        [
          1,
          3
        ]
      ],
      "used_feedback": false,
      "weights": {
        "1->2": 0.073,
        "2->1": 0.2736,
        "2->3": 0.073,
        "3->2": 0.2736,
        "1->3": 0.4832,
        "3->1": 0.2736
      }
    },
    {
      "q": 61,
      "task_id": 82,
      "correct": true,
      "prediction": true,
      "label": true,
      "elapsed": 6.63,
      "path_used": [
        [
          1,
          3
        ]
      ],
      "used_feedback": false,
      "weights": {
        "1->2": 0.0723,
        "2->1": 0.2708,
        "2->3": 0.0723,
        "3->2": 0.2708,
        "1->3": 0.5349,
        "3->1": 0.2708
      }
    },
    {
      "q": 62,
      "task_id": 73,
      "correct": true,
      "prediction": false,
      "label": false,
      "elapsed": 6.3,
      "path_used": [
        [
          1,
          3
        ]
      ],
      "used_feedback": false,
      "weights": {
        "1->2": 0.0716,
        "2->1": 0.2681,
        "2->3": 0.0716,
        "3->2": 0.2681,
        "1->3": 0.5814,
        "3->1": 0.2681
      }
    },
    {
      "q": 63,
      "task_id": 18,
      "correct": true,
      "prediction": false,
      "label": false,
      "elapsed": 6.71,
      "path_used": [
        [
          1,
          3
        ]
      ],
      "used_feedback": false,
      "weights": {
        "1->2": 0.0709,
        "2->1": 0.2655,
        "2->3": 0.0709,
        "3->2": 0.2655,
        "1->3": 0.6233,
        "3->1": 0.2655
      }
    },
    {
      "q": 64,
      "task_id": 86,
      "correct": true,
      "prediction": true,
      "label": true,
      "elapsed": 6.71,
      "path_used": [
        [
          1,
          3
        ]
      ],
      "used_feedback": false,
      "weights": {
        "1->2": 0.0701,
        "2->1": 0.2628,
        "2->3": 0.0701,
        "3->2": 0.2628,
        "1->3": 0.6609,
        "3->1": 0.2628
      }
    },
    {
      "q": 65,
      "task_id": 20,
      "correct": false,
      "prediction": false,
      "label": true,
      "elapsed": 6.55,
      "path_used": [
        [
          1,
          3
        ]
      ],
      "used_feedback": false,
      "weights": {
        "1->2": 0.0694,
        "2->1": 0.2602,
        "2->3": 0.0694,
        "3->2": 0.2602,
        "1->3": 0.4627,
        "3->1": 0.2602
      }
    },
    {
      "q": 66,
      "task_id": 87,
      "correct": true,
      "prediction": true,
      "label": true,
      "elapsed": 6.33,
      "path_used": [
        [
          1,
          3
        ]
      ],
      "used_feedback": false,
      "weights": {
        "1->2": 0.0688,
        "2->1": 0.2576,
        "2->3": 0.0688,
        "3->2": 0.2576,
        "1->3": 0.5164,
        "3->1": 0.2576
      }
    },
    {
      "q": 67,
      "task_id": 23,
      "correct": false,
      "prediction": false,
      "label": true,
      "elapsed": 6.7,
      "path_used": [
        [
          1,
          3
        ]
      ],
      "used_feedback": false,
      "weights": {
        "1->2": 0.0681,
        "2->1": 0.255,
        "2->3": 0.0681,
        "3->2": 0.255,
        "1->3": 0.3615,
        "3->1": 0.255
      }
    },
    {
      "q": 68,
      "task_id": 38,
      "correct": true,
      "prediction": false,
      "label": false,
      "elapsed": 7.67,
      "path_used": [
        [
          1,
          3
        ]
      ],
      "used_feedback": false,
      "weights": {
        "1->2": 0.0674,
        "2->1": 0.2524,
        "2->3": 0.0674,
        "3->2": 0.2524,
        "1->3": 0.4253,
        "3->1": 0.2524
      }
    },
    {
      "q": 69,
      "task_id": 90,
      "correct": true,
      "prediction": false,
      "label": false,
      "elapsed": 6.8,
      "path_used": [
        [
          1,
          3
        ]
      ],
      "used_feedback": false,
      "weights": {
        "1->2": 0.0667,
        "2->1": 0.2499,
        "2->3": 0.0667,
        "3->2": 0.2499,
        "1->3": 0.4828,
        "3->1": 0.2499
      }
    },
    {
      "q": 70,
      "task_id": 0,
      "correct": true,
      "prediction": true,
      "label": true,
      "elapsed": 6.81,
      "path_used": [
        [
          1,
          3
        ]
      ],
      "used_feedback": false,
      "weights": {
        "1->2": 0.066,
        "2->1": 0.2474,
        "2->3": 0.066,
        "3->2": 0.2474,
        "1->3": 0.5345,
        "3->1": 0.2474
      }
    },
    {
      "q": 71,
      "task_id": 42,
      "correct": true,
      "prediction": true,
      "label": true,
      "elapsed": 6.66,
      "path_used": [
        [
          1,
          3
        ]
      ],
      "used_feedback": false,
      "weights": {
        "1->2": 0.0654,
        "2->1": 0.2449,
        "2->3": 0.0654,
        "3->2": 0.2449,
        "1->3": 0.5811,
        "3->1": 0.2449
      }
    },
    {
      "q": 72,
      "task_id": 91,
      "correct": false,
      "prediction": true,
      "label": false,
      "elapsed": 6.47,
      "path_used": [
        [
          1,
          3
        ]
      ],
      "used_feedback": false,
      "weights": {
        "1->2": 0.0647,
        "2->1": 0.2425,
        "2->3": 0.0647,
        "3->2": 0.2425,
        "1->3": 0.4067,
        "3->1": 0.2425
      }
    },
    {
      "q": 73,
      "task_id": 85,
      "correct": true,
      "prediction": true,
      "label": true,
      "elapsed": 7.04,
      "path_used": [
        [
          1,
          3
        ]
      ],
      "used_feedback": false,
      "weights": {
        "1->2": 0.0641,
        "2->1": 0.2401,
        "2->3": 0.0641,
        "3->2": 0.2401,
        "1->3": 0.4661,
        "3->1": 0.2401
      }
    },
    {
      "q": 74,
      "task_id": 74,
      "correct": false,
      "prediction": true,
      "label": false,
      "elapsed": 6.97,
      "path_used": [
        [
          1,
          3
        ]
      ],
      "used_feedback": false,
      "weights": {
        "1->2": 0.0634,
        "2->1": 0.2377,
        "2->3": 0.0634,
        "3->2": 0.2377,
        "1->3": 0.3262,
        "3->1": 0.2377
      }
    },
    {
      "q": 75,
      "task_id": 10,
      "correct": true,
      "prediction": false,
      "label": false,
      "elapsed": 7.32,
      "path_used": [
        [
          1,
          3
        ]
      ],
      "used_feedback": false,
      "weights": {
        "1->2": 0.0628,
        "2->1": 0.2353,
        "2->3": 0.0628,
        "3->2": 0.2353,
        "1->3": 0.3936,
        "3->1": 0.2353
      }
    },
    {
      "q": 76,
      "task_id": 4,
      "correct": true,
      "prediction": true,
      "label": true,
      "elapsed": 6.92,
      "path_used": [
        [
          1,
          3
        ]
      ],
      "used_feedback": false,
      "weights": {
        "1->2": 0.0622,
        "2->1": 0.2329,
        "2->3": 0.0622,
        "3->2": 0.2329,
        "1->3": 0.4543,
        "3->1": 0.2329
      }
    },
    {
      "q": 77,
      "task_id": 11,
      "correct": true,
      "prediction": false,
      "label": false,
      "elapsed": 6.85,
      "path_used": [
        [
          1,
          3
        ]
      ],
      "used_feedback": false,
      "weights": {
        "1->2": 0.0616,
        "2->1": 0.2306,
        "2->3": 0.0616,
        "3->2": 0.2306,
        "1->3": 0.5088,
        "3->1": 0.2306
      }
    },
    {
      "q": 78,
      "task_id": 77,
      "correct": false,
      "prediction": true,
      "label": false,
      "elapsed": 7.26,
      "path_used": [
        [
          1,
          3
        ]
      ],
      "used_feedback": false,
      "weights": {
        "1->2": 0.0609,
        "2->1": 0.2283,
        "2->3": 0.0609,
        "3->2": 0.2283,
        "1->3": 0.3562,
        "3->1": 0.2283
      }
    },
    {
      "q": 79,
      "task_id": 44,
      "correct": true,
      "prediction": true,
      "label": true,
      "elapsed": 6.58,
      "path_used": [
        [
          1,
          3
        ]
      ],
      "used_feedback": false,
      "weights": {
        "1->2": 0.0603,
        "2->1": 0.226,
        "2->3": 0.0603,
        "3->2": 0.226,
        "1->3": 0.4206,
        "3->1": 0.226
      }
    },
    {
      "q": 80,
      "task_id": 67,
      "correct": true,
      "prediction": true,
      "label": true,
      "elapsed": 6.62,
      "path_used": [
        [
          1,
          3
        ]
      ],
      "used_feedback": false,
      "weights": {
        "1->2": 0.0597,
        "2->1": 0.2238,
        "2->3": 0.0597,
        "3->2": 0.2238,
        "1->3": 0.4785,
        "3->1": 0.2238
      }
    },
    {
      "q": 81,
      "task_id": 57,
      "correct": true,
      "prediction": false,
      "label": false,
      "elapsed": 6.81,
      "path_used": [
        [
          1,
          3
        ]
      ],
      "used_feedback": false,
      "weights": {
        "1->2": 0.0591,
        "2->1": 0.2215,
        "2->3": 0.0591,
        "3->2": 0.2215,
        "1->3": 0.5307,
        "3->1": 0.2215
      }
    },
    {
      "q": 82,
      "task_id": 60,
      "correct": false,
      "prediction": false,
      "label": true,
      "elapsed": 6.67,
      "path_used": [
        [
          1,
          3
        ]
      ],
      "used_feedback": false,
      "weights": {
        "1->2": 0.0585,
        "2->1": 0.2193,
        "2->3": 0.0585,
        "3->2": 0.2193,
        "1->3": 0.3715,
        "3->1": 0.2193
      }
    },
    {
      "q": 83,
      "task_id": 55,
      "correct": false,
      "prediction": true,
      "label": false,
      "elapsed": 7.32,
      "path_used": [
        [
          1,
          3
        ]
      ],
      "used_feedback": false,
      "weights": {
        "1->2": 0.058,
        "2->1": 0.2171,
        "2->3": 0.058,
        "3->2": 0.2171,
        "1->3": 0.26,
        "3->1": 0.2171
      }
    },
    {
      "q": 84,
      "task_id": 19,
      "correct": false,
      "prediction": true,
      "label": false,
      "elapsed": 6.95,
      "path_used": [
        [
          1,
          3
        ]
      ],
      "used_feedback": false,
      "weights": {
        "1->2": 0.0574,
        "2->1": 0.2149,
        "2->3": 0.0574,
        "3->2": 0.2149,
        "1->3": 0.182,
        "3->1": 0.2149
      }
    },
    {
      "q": 85,
      "task_id": 52,
      "correct": true,
      "prediction": false,
      "label": false,
      "elapsed": 6.54,
      "path_used": [
        [
          1,
          3
        ]
      ],
      "used_feedback": false,
      "weights": {
        "1->2": 0.0568,
        "2->1": 0.2128,
        "2->3": 0.0568,
        "3->2": 0.2128,
        "1->3": 0.2638,
        "3->1": 0.2128
      }
    },
    {
      "q": 86,
      "task_id": 13,
      "correct": true,
      "prediction": false,
      "label": false,
      "elapsed": 7.92,
      "path_used": [
        [
          1,
          3
        ]
      ],
      "used_feedback": false,
      "weights": {
        "1->2": 0.0562,
        "2->1": 0.2107,
        "2->3": 0.0562,
        "3->2": 0.2107,
        "1->3": 0.3374,
        "3->1": 0.2107
      }
    },
    {
      "q": 87,
      "task_id": 89,
      "correct": true,
      "prediction": true,
      "label": true,
      "elapsed": 6.35,
      "path_used": [
        [
          1,
          3
        ]
      ],
      "used_feedback": false,
      "weights": {
        "1->2": 0.0557,
        "2->1": 0.2086,
        "2->3": 0.0557,
        "3->2": 0.2086,
        "1->3": 0.4037,
        "3->1": 0.2086
      }
    },
    {
      "q": 88,
      "task_id": 17,
      "correct": true,
      "prediction": false,
      "label": false,
      "elapsed": 6.61,
      "path_used": [
        [
          1,
          3
        ]
      ],
      "used_feedback": false,
      "weights": {
        "1->2": 0.0551,
        "2->1": 0.2065,
        "2->3": 0.0551,
        "3->2": 0.2065,
        "1->3": 0.4633,
        "3->1": 0.2065
      }
    },
    {
      "q": 89,
      "task_id": 94,
      "correct": false,
      "prediction": true,
      "label": false,
      "elapsed": 6.92,
      "path_used": [
        [
          1,
          3
        ]
      ],
      "used_feedback": false,
      "weights": {
        "1->2": 0.0546,
        "2->1": 0.2044,
        "2->3": 0.0546,
        "3->2": 0.2044,
        "1->3": 0.3243,
        "3->1": 0.2044
      }
    },
    {
      "q": 90,
      "task_id": 97,
      "correct": false,
      "prediction": true,
      "label": false,
      "elapsed": 6.64,
      "path_used": [
        [
          1,
          3
        ]
      ],
      "used_feedback": false,
      "weights": {
        "1->2": 0.054,
        "2->1": 0.2024,
        "2->3": 0.054,
        "3->2": 0.2024,
        "1->3": 0.227,
        "3->1": 0.2024
      }
    },
    {
      "q": 91,
      "task_id": 47,
      "correct": true,
      "prediction": true,
      "label": true,
      "elapsed": 7.07,
      "path_used": [
        [
          1,
          3
        ]
      ],
      "used_feedback": false,
      "weights": {
        "1->2": 0.0535,
        "2->1": 0.2003,
        "2->3": 0.0535,
        "3->2": 0.2003,
        "1->3": 0.3043,
        "3->1": 0.2003
      }
    },
    {
      "q": 92,
      "task_id": 46,
      "correct": true,
      "prediction": true,
      "label": true,
      "elapsed": 6.47,
      "path_used": [
        [
          1,
          3
        ]
      ],
      "used_feedback": false,
      "weights": {
        "1->2": 0.0529,
        "2->1": 0.1983,
        "2->3": 0.0529,
        "3->2": 0.1983,
        "1->3": 0.3739,
        "3->1": 0.1983
      }
    },
    {
      "q": 93,
      "task_id": 65,
      "correct": false,
      "prediction": false,
      "label": true,
      "elapsed": 7.4,
      "path_used": [
        [
          1,
          3
        ]
      ],
      "used_feedback": false,
      "weights": {
        "1->2": 0.0524,
        "2->1": 0.1964,
        "2->3": 0.0524,
        "3->2": 0.1964,
        "1->3": 0.2617,
        "3->1": 0.1964
      }
    },
    {
      "q": 94,
      "task_id": 56,
      "correct": false,
      "prediction": true,
      "label": false,
      "elapsed": 6.49,
      "path_used": [
        [
          1,
          3
        ]
      ],
      "used_feedback": false,
      "weights": {
        "1->2": 0.0519,
        "2->1": 0.1944,
        "2->3": 0.0519,
        "3->2": 0.1944,
        "1->3": 0.1832,
        "3->1": 0.1944
      }
    },
    {
      "q": 95,
      "task_id": 12,
      "correct": true,
      "prediction": false,
      "label": false,
      "elapsed": 6.7,
      "path_used": [
        [
          1,
          3
        ]
      ],
      "used_feedback": false,
      "weights": {
        "1->2": 0.0514,
        "2->1": 0.1924,
        "2->3": 0.0514,
        "3->2": 0.1924,
        "1->3": 0.2649,
        "3->1": 0.1924
      }
    },
    {
      "q": 96,
      "task_id": 66,
      "correct": false,
      "prediction": false,
      "label": true,
      "elapsed": 6.99,
      "path_used": [
        [
          1,
          3
        ]
      ],
      "used_feedback": false,
      "weights": {
        "1->2": 0.0509,
        "2->1": 0.1905,
        "2->3": 0.0509,
        "3->2": 0.1905,
        "1->3": 0.1854,
        "3->1": 0.1905
      }
    },
    {
      "q": 97,
      "task_id": 41,
      "correct": true,
      "prediction": true,
      "label": true,
      "elapsed": 7.06,
      "path_used": [
        [
          1,
          3
        ]
      ],
      "used_feedback": false,
      "weights": {
        "1->2": 0.0503,
        "2->1": 0.1886,
        "2->3": 0.0503,
        "3->2": 0.1886,
        "1->3": 0.2669,
        "3->1": 0.1886
      }
    },
    {
      "q": 98,
      "task_id": 49,
      "correct": true,
      "prediction": true,
      "label": true,
      "elapsed": 6.79,
      "path_used": [
        [
          1,
          3
        ]
      ],
      "used_feedback": false,
      "weights": {
        "1->2": 0.0498,
        "2->1": 0.1867,
        "2->3": 0.0498,
        "3->2": 0.1867,
        "1->3": 0.3402,
        "3->1": 0.1867
      }
    },
    {
      "q": 99,
      "task_id": 61,
      "correct": true,
      "prediction": true,
      "label": true,
      "elapsed": 7.01,
      "path_used": [
        [
          1,
          3
        ]
      ],
      "used_feedback": false,
      "weights": {
        "1->2": 0.0493,
        "2->1": 0.1849,
        "2->3": 0.0493,
        "3->2": 0.1849,
        "1->3": 0.4062,
        "3->1": 0.1849
      }
    },
    {
      "q": 100,
      "task_id": 2,
      "correct": true,
      "prediction": true,
      "label": true,
      "elapsed": 6.88,
      "path_used": [
        [
          1,
          3
        ]
      ],
      "used_feedback": false,
      "weights": {
        "1->2": 0.0489,
        "2->1": 0.183,
        "2->3": 0.0489,
        "3->2": 0.183,
        "1->3": 0.4656,
        "3->1": 0.183
      }
    }
  ]
}